Metadata-Version: 2.4
Name: adafruit-circuitpython-ws2801
Version: 1.0.3
Summary: CircuitPython library for WS2801 LEDs.
Author-email: Adafruit Industries <circuitpython@adafruit.com>
License: MIT
Project-URL: Homepage, https://github.com/adafruit/Adafruit_CircuitPython_WS2801
Keywords: adafruit,ws2801,leds,led,rgb,hardware,micropython,circuitpython
Classifier: Intended Audience :: Developers
Classifier: Topic :: Software Development :: Libraries
Classifier: Topic :: Software Development :: Embedded Systems
Classifier: Topic :: System :: Hardware
Classifier: License :: OSI Approved :: MIT License
Classifier: Programming Language :: Python :: 3
License-File: LICENSE
Requires-Dist: Adafruit-Blinka
Requires-Dist: adafruit-circuitpython-busdevice
Requires-Dist: adafruit-circuitpython-pixelbuf
Provides-Extra: optional
Dynamic: license-file
